LICENCE
README.md
setup.py
fastapi_event/__init__.py
fastapi_event/base.py
fastapi_event/exceptions.py
fastapi_event/handler.py
fastapi_event/listener.py
fastapi_event/middleware.py
fastapi_event.egg-info/PKG-INFO
fastapi_event.egg-info/SOURCES.txt
fastapi_event.egg-info/dependency_links.txt
fastapi_event.egg-info/requires.txt
fastapi_event.egg-info/top_level.txt
tests/__init__.py
tests/conftest.py
tests/events.py
tests/test_handler.py
tests/test_listener.py
tests/test_middleware.py
tests/test_validator.py