Metadata-Version: 2.1
Name: fastapi-event
Version: 0.1.0
Summary: Event dispatcher for FastAPI
Home-page: https://github.com/teamhide/fastapi-event
Author: Hide
Author-email: padocon@naver.com
License: UNKNOWN
Platform: UNKNOWN
Classifier: Intended Audience :: Developers
Classifier: Programming Language :: Python
Classifier: Programming Language :: Python :: 3.7
Classifier: Programming Language :: Python :: 3.8
Classifier: Programming Language :: Python :: 3.9
Classifier: License :: OSI Approved :: Apache Software License
Classifier: Operating System :: OS Independent
Requires-Python: >=3.7
License-File: LICENCE
